migrations/0001_initial.py
migrations/__init__.py
restrict_logins-1.0.1.dist-info/licenses/LICENSE
restrict_logins-1.0.1.dist-info/METADATA
restrict_logins-1.0.1.dist-info/WHEEL
restrict_logins-1.0.1.dist-info/top_level.txt
restrict_logins-1.0.1.dist-info/RECORD
